{
  "guests": [
    {
      "id": "1",
      "first_name": "John",
      "last_name": "Doe",
      "company_name": "Company A"
    },
    {
      "id": "2",
      "first_name": "Jane",
      "last_name": "Doe",
      "company_name": "Company B"
    },
    {
      "id": "3",
      "first_name": "Mike",
      "last_name": "Ross",
      "company_name": "Company C"
    },
    {
      "id": "4",
      "first_name": "Rachel",
      "last_name": "Zane",
      "company_name": "Company D"
    },
    {
      "id": "5",
      "first_name": "Harvey",
      "last_name": "Specter",
      "company_name": "Company E"
    },
    {
      "id": "ca91",
      "first_name": "Testt",
      "last_name": "test333",
      "company_name": "sdefsdf"
    }
  ],
  "staff": [
    {
      "id": "1",
      "first_name": "Alice",
      "last_name": "Smith"
    },
    {
      "id": "2",
      "first_name": "Bob",
      "last_name": "Johnson"
    },
    {
      "id": "3",
      "first_name": "Charlie",
      "last_name": "Brown"
    },
    {
      "id": "4",
      "first_name": "David",
      "last_name": "Williams"
    },
    {
      "id": "5",
      "first_name": "Eve",
      "last_name": "Davis"
    },
    {
      "id": "6",
      "first_name": "Frank",
      "last_name": "Miller"
    },
    {
      "id": "7",
      "first_name": "Grace",
      "last_name": "Wilson"
    },
    {
      "id": "8",
      "first_name": "Henry",
      "last_name": "Moore"
    },
    {
      "id": "9",
      "first_name": "Ivy",
      "last_name": "Taylor"
    },
    {
      "id": "10",
      "first_name": "Jack",
      "last_name": "Anderson"
    },
    {
      "id": "11",
      "first_name": "Katie",
      "last_name": "Thomas"
    },
    {
      "id": "12",
      "first_name": "Leo",
      "last_name": "Jackson"
    },
    {
      "id": "13",
      "first_name": "Mia",
      "last_name": "White"
    },
    {
      "id": "14",
      "first_name": "Nathan",
      "last_name": "Harris"
    },
    {
      "id": "15",
      "first_name": "Olivia",
      "last_name": "Martin"
    },
    {
      "id": "16",
      "first_name": "Peter",
      "last_name": "Thompson"
    },
    {
      "id": "17",
      "first_name": "Quincy",
      "last_name": "Garcia"
    },
    {
      "id": "18",
      "first_name": "Rachel",
      "last_name": "Martinez"
    },
    {
      "id": "19",
      "first_name": "Sam",
      "last_name": "Robinson"
    },
    {
      "id": "20",
      "first_name": "Tina",
      "last_name": "Clark"
    }
  ],
  "attendances": [
    {
      "id": "b6f3",
      "user_type": "staff",
      "event_type": "check_in"
    },
    {
      "id": "270d",
      "user_type": "staff",
      "event_type": "check_in"
    },
    {
      "id": "d1b9",
      "user_type": "guest",
      "event_type": "check_in"
    },
    {
      "id": "7adb",
      "user_type": "staff",
      "event_type": "check_in"
    },
    {
      "id": "1207",
      "user_type": "staff",
      "event_type": "check_in"
    },
    {
      "id": "67eb",
      "user_type": "guest",
      "event_type": "check_in"
    },
    {
      "id": "822c",
      "user_type": "staff",
      "event_type": "check_in"
    },
    {
      "id": "6f8d",
      "user_type": "staff",
      "event_type": "check_in"
    }
  ]
}
